.DS_Store
nms_3d/__init__.py
nms_3d/nms_3d.py
nms_3d/plot_3d_boxes.py
nms_3d-0.1.6.dist-info/LICENSE
nms_3d-0.1.6.dist-info/METADATA
nms_3d-0.1.6.dist-info/WHEEL
nms_3d-0.1.6.dist-info/top_level.txt
nms_3d-0.1.6.dist-info/RECORD
