Metadata-Version: 2.1
Name: nms-3d
Version: 0.1.6
Summary: 3D bounding box NMS and plotting package
Home-page: https://github.com/GiulioRusso/NMS-3D
Author: Giulio Russo, Ciro Russo
Author-email: russogiulio1998@icloud.com, ciro.russo2910@gmail.com
License: MIT License
Platform: UNKNOWN
Classifier: Programming Language :: Python :: 3
Classifier: License :: OSI Approved :: MIT License
Classifier: Operating System :: OS Independent
Requires-Python: >=3.9.5
License-File: LICENSE
Requires-Dist: torch>=2.2.2
Requires-Dist: plotly>=5.13.1
